watanpy/__init__.py
watanpy1-22.dist-info/licenses/LICENSE.txt
watanpy1-22.dist-info/METADATA
watanpy1-22.dist-info/WHEEL
watanpy1-22.dist-info/top_level.txt
watanpy1-22.dist-info/RECORD
